sportsvision/__init__.py
sportsvision/research/__init__.py
sportsvision/research/configs.py
sportsvision/research/models.py
sportsvision/research/utils.py
sportsvision-0.1.0.dist-info/METADATA
sportsvision-0.1.0.dist-info/WHEEL
sportsvision-0.1.0.dist-info/top_level.txt
sportsvision-0.1.0.dist-info/RECORD
