Metadata-Version: 2.2
Name: sportsvision
Version: 0.1.0
Summary: Sports Vision Research Tools
Home-page: https://huggingface.co/sportsvision
Author: Varun Kodathala
Author-email: varun@sportsvision.ai
License: MIT
Keywords: text embeddings,image embeddings,multi modal embeddings,unified embeddings
Classifier: Development Status :: 3 - Alpha
Classifier: Intended Audience :: Science/Research
Classifier: Intended Audience :: Developers
Classifier: License :: OSI Approved :: MIT License
Classifier: Programming Language :: Python :: 3.7
Classifier: Programming Language :: Python :: 3.8
Classifier: Programming Language :: Python :: 3.9
Classifier: Programming Language :: Python :: 3.10
Classifier: Programming Language :: Python :: 3.11
Classifier: Operating System :: OS Independent
Classifier: Topic :: Scientific/Engineering :: Artificial Intelligence
Classifier: Topic :: Software Development :: Libraries
Requires-Python: >=3.7, <4
Requires-Dist: torch<3.0.0,>=1.12.0
Requires-Dist: transformers<5.0.0,>=4.26.0
Requires-Dist: pillow<12.0.0,>=9.0.0
Requires-Dist: tqdm<5.0.0,>=4.64.0
Dynamic: author
Dynamic: author-email
Dynamic: classifier
Dynamic: description
Dynamic: description-content-type
Dynamic: home-page
Dynamic: keywords
Dynamic: license
Dynamic: requires-dist
Dynamic: requires-python
Dynamic: summary
